fbx_tool/__init__.py
fbx_tool/cli.py
fbx_tool-0.1.0.dist-info/licenses/LICENSE
fbx_tool-0.1.0.dist-info/METADATA
fbx_tool-0.1.0.dist-info/WHEEL
fbx_tool-0.1.0.dist-info/entry_points.txt
fbx_tool-0.1.0.dist-info/top_level.txt
fbx_tool-0.1.0.dist-info/RECORD
