Metadata-Version: 2.4
Name: fbx-tool
Version: 0.1.0
Summary: Filter FBX meshes by name patterns and export sampled point clouds (PCD).
Author-email: Felipe Cadar <cadar@dcc.ufmg.br>
License: MIT
Classifier: Programming Language :: Python :: 3
Classifier: License :: OSI Approved :: MIT License
Classifier: Operating System :: OS Independent
Classifier: Topic :: Scientific/Engineering :: Visualization
Classifier: Intended Audience :: Developers
Requires-Python: >=3.12
License-File: LICENSE
Requires-Dist: fbxloader>=0.0.2
Requires-Dist: open3d>=0.19.0
Requires-Dist: rerun-sdk>=0.25.1
Provides-Extra: dev
Requires-Dist: ipdb>=0.13.13; extra == "dev"
Dynamic: license-file
